osmhm/__init__.py
osmhm/config.py
osmhm/connect.py
osmhm/fetch.py
osmhm/filters.py
osmhm/inserts.py
osmhm/manage.py
osmhm/models.py
osmhm/queries.py
osmhm/send_notification.py
osmhm/tables.py
osm_hall_monitor-0.52.2.dist-info/LICENSE
osm_hall_monitor-0.52.2.dist-info/METADATA
osm_hall_monitor-0.52.2.dist-info/WHEEL
osm_hall_monitor-0.52.2.dist-info/top_level.txt
osm_hall_monitor-0.52.2.dist-info/RECORD
