Metadata-Version: 2.1
Name: osm-hall-monitor
Version: 0.52.2
Summary: Passive changeset monitoring for OpenStreetMap.
Home-page: http://github.com/ethan-nelson/osm_hall_monitor
Author: Ethan Nelson
Author-email: git@ethan-nelson.com
License: MIT
Platform: UNKNOWN
Requires-Dist: osm-diff-tool
Requires-Dist: psycopg2-binary
